MANIFEST.in
procurement_pull_workflow.xml
setup.py
stock_location_demo_cpu1.xml
stock_location_demo_cpu3.yml
stock_location_view.xml
./__init__.py
./__openerp__.py
./procurement_pull.py
./stock_location.py
i18n/ar.po
i18n/bg.po
i18n/bs.po
i18n/ca.po
i18n/cs.po
i18n/da.po
i18n/de.po
i18n/el.po
i18n/es.po
i18n/es_AR.po
i18n/es_CL.po
i18n/es_CR.po
i18n/es_MX.po
i18n/es_VE.po
i18n/et.po
i18n/fi.po
i18n/fr.po
i18n/gl.po
i18n/hr.po
i18n/hu.po
i18n/id.po
i18n/it.po
i18n/ja.po
i18n/ko.po
i18n/lt.po
i18n/lv.po
i18n/mk.po
i18n/mn.po
i18n/nb.po
i18n/nl.po
i18n/nl_BE.po
i18n/pl.po
i18n/pt.po
i18n/pt_BR.po
i18n/ro.po
i18n/ru.po
i18n/sl.po
i18n/sq.po
i18n/stock_location.pot
i18n/sv.po
i18n/th.po
i18n/tlh.po
i18n/tr.po
i18n/uk.po
i18n/vi.po
i18n/zh_CN.po
i18n/zh_TW.po
images/pulled_flow.jpeg
images/pushed_flow.jpeg
openerp_stock_location.egg-info/PKG-INFO
openerp_stock_location.egg-info/SOURCES.txt
openerp_stock_location.egg-info/dependency_links.txt
openerp_stock_location.egg-info/requires.txt
openerp_stock_location.egg-info/top_level.txt
security/ir.model.access.csv
security/stock_location_security.xml
test/stock_location_pull_flow.yml
test/stock_location_push_flow.yml